rewrite_remote/__init__.py
rewrite_remote/client.py
rewrite_remote/event.py
rewrite_remote/receiver.py
rewrite_remote/remote_utils.py
rewrite_remote/remoting.py
rewrite_remote/sender.py
rewrite_remote/server.py
rewrite_remote/type_utils.py
rewrite_remote/handlers/__init__.py
rewrite_remote/handlers/handler_helpers.py
rewrite_remote/handlers/hello_world_handler.py
rewrite_remote/handlers/list_projects_handler.py
rewrite_remote/handlers/parse_project_sources_handler.py
rewrite_remote/handlers/parse_source_handler.py
rewrite_remote/handlers/project_helper.py
rewrite_remote/handlers/pypi_manager.py
rewrite_remote/handlers/recipe_install_handler.py
rewrite_remote/handlers/run_recipe_load_and_visitor_handler.py
rewrite_remote/handlers/types.py
openrewrite_remote-0.28.0.dist-info/METADATA
openrewrite_remote-0.28.0.dist-info/WHEEL
openrewrite_remote-0.28.0.dist-info/entry_points.txt
openrewrite_remote-0.28.0.dist-info/top_level.txt
openrewrite_remote-0.28.0.dist-info/RECORD
