Metadata-Version: 2.4
Name: openrewrite-remote
Version: 0.28.0
Summary: Remoting functionality for the OpenRewrite library.
Author-email: "Moderne Inc." <support@moderne.io>
License: Moderne, Inc. Commercial License
Requires-Python: <4,>=3.9
Requires-Dist: cbor2==5.6.5
Requires-Dist: openrewrite
Requires-Dist: pip>=24.3.1
Requires-Dist: pypi-simple>=1.6.1
Requires-Dist: toml>=0.10.2
